pymouth/__init__.py
pymouth/adapter.py
pymouth/analyser.py
pymouth/audio_devices_utils.py
pymouth/vts_websockets.py
pymouth-1.3.2.dist-info/METADATA
pymouth-1.3.2.dist-info/WHEEL
pymouth-1.3.2.dist-info/licenses/LICENSE
pymouth-1.3.2.dist-info/RECORD
