Metadata-Version: 2.4
Name: pymouth
Version: 1.3.2
Summary: Live2D Mouth-sync artifact
Project-URL: Homepage, https://github.com/organics2016/pymouth
Project-URL: Documentation, https://github.com/organics2016/pymouth
Project-URL: Source, https://github.com/organics2016/pymouth
Project-URL: Issues, https://github.com/organics2016/pymouth/issues
Author-email: organics2016 <organics2015@outlook.com>
License-File: LICENSE
Classifier: License :: OSI Approved :: MIT License
Classifier: Operating System :: MacOS
Classifier: Operating System :: Microsoft :: Windows
Classifier: Operating System :: POSIX
Classifier: Operating System :: POSIX :: Linux
Classifier: Operating System :: Unix
Classifier: Programming Language :: Python :: 3
Classifier: Topic :: Software Development :: Libraries
Requires-Python: >=3.10
Requires-Dist: dtw-python~=1.5.3
Requires-Dist: librosa~=0.11.0
Requires-Dist: numpy~=2.0.2
Requires-Dist: pyaudio~=0.2.14
Requires-Dist: sounddevice~=0.4.7
Requires-Dist: soundfile~=0.12.1
Requires-Dist: websockets~=15.0.1
